robo_appian/__init__.py
robo_appian/components/ButtonUtils.py
robo_appian/components/DateUtils.py
robo_appian/components/DropdownUtils.py
robo_appian/components/InputUtils.py
robo_appian/components/LabelUtils.py
robo_appian/components/LinkUtils.py
robo_appian/components/SearchDropdownUtils.py
robo_appian/components/SearchInputUtils.py
robo_appian/components/TabUtils.py
robo_appian/components/TableUtils.py
robo_appian/controllers/ComponentDriver.py
robo_appian/exceptions/MyCustomError.py
robo_appian/utils/BrowserUtils.py
robo_appian/utils/ComponentUtils.py
robo_appian/utils/RoboUtils.py
robo_appian-0.0.35.dist-info/METADATA
robo_appian-0.0.35.dist-info/WHEEL
robo_appian-0.0.35.dist-info/licenses/LICENSE
robo_appian-0.0.35.dist-info/RECORD
