Metadata-Version: 2.4
Name: robo_appian
Version: 0.0.35
Summary: Automate your Appian code testing with Python. Boost quality, save time.
License: Apache-2.0
License-File: LICENSE
Author: Dinil Mithra
Author-email: dinilmithra.mailme@gmail.com
Requires-Python: >=3.12,<4.0
Classifier: License :: OSI Approved :: Apache Software License
Classifier: Operating System :: OS Independent
Classifier: Programming Language :: Python :: 3
Classifier: Programming Language :: Python :: 3.12
Classifier: Programming Language :: Python :: 3.13
Classifier: Programming Language :: Python :: 3.14
Requires-Dist: numpy
Requires-Dist: requests (>=2.25.1,<3.0.0)
Requires-Dist: selenium (>=4.34.0)
Project-URL: Homepage, https://github.com/dinilmithra/robo_appian
Project-URL: Repository, https://github.com/dinilmithra/robo_appian.git
